LICENSE
MANIFEST.in
README.md
setup.cfg
setup.py
core/__init__.py
core/admin.py
core/apps.py
core/models.py
core/serializers.py
core/tests.py
core/urls.py
core/views.py
core/migrations/0001_initial.py
core/migrations/__init__.py
django_keycloak_auth/__init__.py
django_keycloak_auth/decorators.py
django_keycloak_auth/keycloak.py
django_keycloak_auth/middleware.py
django_keycloak_auth/settings.py
django_keycloak_auth/tests.py
django_keycloak_auth/urls.py
django_keycloak_auth/wsgi.py
django_keycloak_auth.egg-info/PKG-INFO
django_keycloak_auth.egg-info/SOURCES.txt
django_keycloak_auth.egg-info/dependency_links.txt
django_keycloak_auth.egg-info/requires.txt
django_keycloak_auth.egg-info/top_level.txt