Metadata-Version: 2.1
Name: django-keycloak-auth
Version: 1.0.0
Summary: Django Keycloak Auth is Python package providing access to the Keycloak API.
Home-page: https://github.com/marcelo225/django-keycloak-auth
Author: Marcelo Vinicius
Author-email: mr.225@hotmail.com
License: UNKNOWN
Project-URL: Funding, https://donate.pypi.org
Project-URL: Say Thanks!, https://github.com/marcelo225/django-keycloak-auth
Project-URL: Source, https://github.com/marcelo225/django-keycloak-auth
Project-URL: Tracker, https://github.com/marcelo225/django-keycloak-auth/issues
Keywords: keycloak django roles authentication authorization
Platform: UNKNOWN
Classifier: Framework :: Django
Classifier: Intended Audience :: Developers
Classifier: License :: OSI Approved :: MIT License
Classifier: Operating System :: OS Independent
Classifier: Programming Language :: Python :: 3
Classifier: Programming Language :: Python :: 3.5
